Workbook
Name aporte: Planilha1!$D$16
Name patrimonio: Planilha1!$D$19
Name Perfil: Planilha1!$D$28
Name qtd_anos: Planilha1!$D$17
Name Rend: Planilha1!$D$12
Name Salario: Planilha1!$D$11
Name Sug_Invest: Planilha1!$D$13
Name taxa_mensal: Planilha1!$D$18
Name Valor_invest: Planilha1!$D$29

Sheet Planilha1
B10: CONFIGURAÇÕES
B11: Salário | D11: 4500
B12: Rendimento Carteira | D12: 0.01079
B13: Sugestão de Investimento | D13: =Salario*0.3 -> 1350
B15: INVESTIMENTO MENSAL
B16: Quanto investir por mês? | D16: 200
B17: Por quantos anos? | D17: 10
B18: Taxa de Rendimento Mensal | D18: =Rend -> 0.01079
B19: Patrimônio acumulado | D19: =FV(taxa_mensal,qtd_anos*12,aporte*-1) -> 48656.843
B20: Dividendos Mensais | D20: =patrimonio*taxa_mensal -> 525.00733
B22: Cenários | D22: Dividendo
A23: 2 | B23: Quanto em 2 Anos? | C23: =FV(taxa_mensal,A23*12,aporte*-1) -> 5445.5255 | D23: =C23*taxa_mensal -> 58.75722
A24: 5 | B24: Quanto em 5 Anos? | C24: =FV(taxa_mensal,A24*12,aporte*-1) -> 16755.383 | D24: =C24*taxa_mensal -> 180.79058
A25: 10 | B25: Quanto em 10 Anos? | C25: =FV(taxa_mensal,A25*12,aporte*-1) -> 48656.843 | D25: =C25*taxa_mensal -> 525.00733
A26: 20 | B26: Quanto em 20 Anos? | C26: =FV(taxa_mensal,A26*12,aporte*-1) -> 225039.68 | D26: =C26*taxa_mensal -> 2428.1781
B28: Perfil de investidor | D28: Moderado
B29: Valor a ser investidor por mês | D29: 400
B31: TIPO DE FII | C31: Percentual Sugerido | D31: Valores
B32: PAPEL | C32: =VLOOKUP(Perfil&"-"&B32,Planilha2!A:D,4,FALSE) -> 0.32 | D32: =C32*Valor_invest -> 128
B33: TIJOLO | C33: =VLOOKUP(Perfil&"-"&B33,Planilha2!A:D,4,FALSE) -> 0.35 | D33: =C33*Valor_invest -> 140
B34: HÍBRIDOS | C34: =VLOOKUP(Perfil&"-"&B34,Planilha2!A:D,4,FALSE) -> 0.08 | D34: =C34*Valor_invest -> 32
B35: FOF's | C35: =VLOOKUP(Perfil&"-"&B35,Planilha2!A:D,4,FALSE) -> 0.05 | D35: =C35*Valor_invest -> 20
B36: DESENVOLVIMENTO | C36: =VLOOKUP(Perfil&"-"&B36,Planilha2!A:D,4,FALSE) -> 0.1 | D36: =C36*Valor_invest -> 40
B37: HOTELARIAS | C37: =VLOOKUP(Perfil&"-"&B37,Planilha2!A:D,4,FALSE) -> 0.1 | D37: =C37*Valor_invest -> 40

Sheet Planilha2
A2: CHAVE | B2: PERFIL | C2: TIPO DE FII | D2: %
A3: Conservador-PAPEL | B3: Conservador | C3: PAPEL | D3: 0.3
A4: Conservador-TIJOLO | B4: Conservador | C4: TIJOLO | D4: 0.5
A5: Conservador-HÍBRIDOS | B5: Conservador | C5: HÍBRIDOS | D5: 0.1
A6: Con'servador-FOF's | B6: Conservador | C6: FOFs | D6: 0.1
A7: Conservador-DESENVOLVIMENTO | B7: Conservador | C7: DESENVOLVIMENTO | D7: 0
A8: Conservador-HOTELARIAS | B8: Conservador | C8: HOTELARIAS | D8: 0
A9: Moderado-PAPEL | B9: Moderado | C9: PAPEL | D9: 0.32
A10: Moderado-TIJOLO | B10: Moderado | C10: TIJOLO | D10: 0.35
A11: Moderado-HÍBRIDOS | B11: Moderado | C11: HÍBRIDOS | D11: 0.08
A12: Moderado-FOF's | B12: Moderado | C12: FOFs | D12: 0.05
A13: Moderado-DESENVOLVIMENTO | B13: Moderado | C13: DESENVOLVIMENTO | D13: 0.1
A14: Moderado-HOTELARIAS | B14: Moderado | C14: HOTELARIAS | D14: 0.1
... A20: Agressivo-HOTELARIAS | B20: Agressivo | C20: HOTELARIAS | D20: 0.1
